[
    {
      "name": "Classic Shortboard",
      "type": "Shortboard",
      "price": 450.00,
      "description": "Used shortboard, great for advanced surfers tackling larger waves. Some minor dings, fully repaired.",
      "image": "ClassicShortboard.png",
      "quantity_available": 3
    },
    {
      "name": "Sunset Longboard",
      "type": "Longboard",
      "price": 550.00,
      "description": "Gently used longboard, perfect for beginners. Stable and easy to ride.",
      "image": "SunsetLongboard.png",
      "quantity_available": 2
    },
    {
      "name": "Retro Fish",
      "type": "Fish",
      "price": 400.00,
      "description": "Vintage fish surfboard, ideal for small to medium waves. Very good condition.",
      "image": "RetroFish.png",
      "quantity_available": 5
    },
    {
      "name": "Hybrid Funboard",
      "type": "Funboard",
      "price": 480.00,
      "description": "A versatile funboard, suitable for a wide range of wave sizes. Excellent for intermediate surfers.",
      "image": "HybridFunboard.png",
      "quantity_available": 4
    },
    {
      "name": "Big Wave Gun",
      "type": "Gun",
      "price": 600.00,
      "description": "Designed for big wave surfing. Long, sleek, and fast. In excellent condition.",
      "image": "BigWaveGun.png",
      "quantity_available": 1
    }
  ]
  